python_core/__init__.py
python_core/python_core.py
python_core/exceptions/__init__.py
python_core/exceptions/exceptions.py
abstract_python_core-1.1.0.dist-info/LICENSE
abstract_python_core-1.1.0.dist-info/METADATA
abstract_python_core-1.1.0.dist-info/WHEEL
abstract_python_core-1.1.0.dist-info/top_level.txt
abstract_python_core-1.1.0.dist-info/RECORD
