Metadata-Version: 2.1
Name: abstract-python-core
Version: 1.1.0
Summary: AbstractAPI Python Core Library - Used by the other Abstract API libraries.
Home-page: https://github.com/abstractapi/python-core
Author: Benjamin Bouchet
Author-email: libraries@abstractapi.com
License: UNKNOWN
Platform: UNKNOWN
Classifier: Programming Language :: Python :: 3.6
Classifier: Intended Audience :: Developers
Classifier: License :: OSI Approved :: MIT License
Requires-Dist: requests (>=2)
